astro_sedpy-0.4.0.dist-info/licenses/LICENSE
sedpy/__init__.py
sedpy/_version.py
sedpy/attenuation.py
sedpy/extinction.py
sedpy/observate.py
sedpy/reference_spectra.py
sedpy/smoothing.py
sedpy/boneyard/ds9region.py
sedpy/boneyard/image.py
sedpy/boneyard/modelgrid.py
sedpy/boneyard/photometer.py
sedpy/boneyard/plotsed.py
sedpy/data/alpha_lyr_stis_005.fits
sedpy/data/alpha_lyr_stis_011.fits
sedpy/data/sun_kurucz93.fits
sedpy/data/filters/README.md
sedpy/data/filters/README_herschel
sedpy/data/filters/README_wise
sedpy/data/filters/acs_wfc_f435w.par
sedpy/data/filters/acs_wfc_f475w.par
sedpy/data/filters/acs_wfc_f555w.par
sedpy/data/filters/acs_wfc_f606w.par
sedpy/data/filters/acs_wfc_f625w.par
sedpy/data/filters/acs_wfc_f775w.par
sedpy/data/filters/acs_wfc_f814w.par
sedpy/data/filters/acs_wfc_f850lp.par
sedpy/data/filters/bass_g.par
sedpy/data/filters/bass_r.par
sedpy/data/filters/bessell_B.par
sedpy/data/filters/bessell_I.par
sedpy/data/filters/bessell_R.par
sedpy/data/filters/bessell_U.par
sedpy/data/filters/bessell_V.par
sedpy/data/filters/cfht_megacam_gs_9401.par
sedpy/data/filters/cfht_megacam_is_9701.par
sedpy/data/filters/cfht_megacam_rs_9601.par
sedpy/data/filters/cfht_megacam_us_9301.par
sedpy/data/filters/cfht_megacam_zs_9801.par
sedpy/data/filters/cfht_wircam_H_8201.par
sedpy/data/filters/cfht_wircam_J_8101.par
sedpy/data/filters/cfht_wircam_Ks_8302.par
sedpy/data/filters/decam_Y.par
sedpy/data/filters/decam_g.par
sedpy/data/filters/decam_i.par
sedpy/data/filters/decam_r.par
sedpy/data/filters/decam_u.par
sedpy/data/filters/decam_z.par
sedpy/data/filters/gaia_bp.par
sedpy/data/filters/gaia_bp_dr2rev.par
sedpy/data/filters/gaia_g.par
sedpy/data/filters/gaia_g_dr2rev.par
sedpy/data/filters/gaia_rp.par
sedpy/data/filters/gaia_rp_dr2rev.par
sedpy/data/filters/galex_FUV.par
sedpy/data/filters/galex_NUV.par
sedpy/data/filters/herschel_pacs_100.par
sedpy/data/filters/herschel_pacs_160.par
sedpy/data/filters/herschel_pacs_70.par
sedpy/data/filters/herschel_spire_250.par
astro_sedpy-0.4.0.dist-info/METADATA
astro_sedpy-0.4.0.dist-info/WHEEL
astro_sedpy-0.4.0.dist-info/top_level.txt
astro_sedpy-0.4.0.dist-info/RECORD
