Metadata-Version: 2.4
Name: astro-sedpy
Version: 0.4.0
Summary: Simple tools for astronomical spectral energy distributions, particularly filter projections.
Author-email: Benjamin Johnson <benjamin.johnson@cfa.harvard.edu>
License: MIT License
Classifier: Development Status :: 5 - Production/Stable
Classifier: Intended Audience :: Developers
Classifier: Intended Audience :: Science/Research
Classifier: License :: OSI Approved :: MIT License
Classifier: Operating System :: OS Independent
Classifier: Programming Language :: Python
License-File: LICENSE
Requires-Dist: numpy
Requires-Dist: astropy
Dynamic: license-file
